engine_grpc/__init__.py
engine_grpc/engine_pipe_abstract.py
engine_grpc/engine_pipe_channel.py
engine_grpc/engine_pipe_decorator.py
engine_grpc/engine_pipe_impl.py
engine_grpc/engine_pipe_server.py
engine_grpc/engine_stub_interface.py
engine_grpc/unity/__init__.py
engine_grpc/unity/engine_pipe_unity_impl.py
engine_grpc/unreal/__init__.py
engine_grpc/unreal/engine_pipe_unreal_impl.py
engine_grpc/utils/__init__.py
engine_grpc/utils/component_assemble.py
engine_grpc/utils/const_key.py
engine_grpc/utils/singleton.py
engine_grpc/utils/sys_process.py
engine_grpc-0.3.3.dist-info/METADATA
engine_grpc-0.3.3.dist-info/WHEEL
engine_grpc-0.3.3.dist-info/top_level.txt
engine_grpc-0.3.3.dist-info/RECORD
